numpy2ometiff/__init__.py
numpy2ometiff/writer.py
numpy2ometiff-0.1.4.dist-info/LICENSE
numpy2ometiff-0.1.4.dist-info/METADATA
numpy2ometiff-0.1.4.dist-info/WHEEL
numpy2ometiff-0.1.4.dist-info/top_level.txt
numpy2ometiff-0.1.4.dist-info/RECORD
