Metadata-Version: 2.1
Name: numpy2ometiff
Version: 0.1.4
Summary: Convert NumPy arrays to OME-TIFF
Home-page: https://github.com/TristanWhitmarsh/numpy2ometiff
Author: Tristan Whitmarsh
Author-email: tw401@cam.ac.uk
Classifier: Development Status :: 3 - Alpha
Classifier: Intended Audience :: Science/Research
Classifier: License :: OSI Approved :: BSD License
Classifier: Programming Language :: Python :: 3
Classifier: Topic :: Scientific/Engineering :: Bio-Informatics
Requires-Python: >=3.6
License-File: LICENSE
Requires-Dist: numpy
Requires-Dist: tifffile
Requires-Dist: scikit-image
